stylia/__init__.py
stylia/_clean_static_version.py
stylia/_clean_version.py
stylia/_static_version.py
stylia/_version.py
stylia/colors/__init__.py
stylia/colors/colors.py
stylia/figure/__init__.py
stylia/figure/figure.py
stylia/gallery/__init__.py
stylia/sizes/__init__.py
stylia/sizes/sizes.py
stylia/utils/__init__.py
stylia/vars.py
stylia-0.0.2.dist-info/METADATA
stylia-0.0.2.dist-info/WHEEL
stylia-0.0.2.dist-info/licenses/LICENSE
stylia-0.0.2.dist-info/RECORD
