Metadata-Version: 2.4
Name: stylia
Version: 0.0.2
Summary: Acceptable figure styles for scientific publications
License: MIT
License-File: LICENSE
Author: Miquel Duran-Frigola
Author-email: miquel@ersilia.io
Requires-Python: >=3.8
Classifier: License :: OSI Approved :: MIT License
Classifier: Programming Language :: Python :: 3
Classifier: Programming Language :: Python :: 3.8
Classifier: Programming Language :: Python :: 3.9
Classifier: Programming Language :: Python :: 3.10
Classifier: Programming Language :: Python :: 3.11
Classifier: Programming Language :: Python :: 3.12
Classifier: Programming Language :: Python :: 3.13
Classifier: Programming Language :: Python :: 3.14
Requires-Dist: cmcrameri (>=1.7)
Requires-Dist: matplotlib (>=3.7.1)
Requires-Dist: palettable (>=3.3.2)
Requires-Dist: scikit-learn (>=1.2.2)
Requires-Dist: seaborn (>=0.12.2)
